[
  {
    "id": "TM-001",
    "teamId": "TEAM-001",
    "personnelId": "PER-002",
    "createdAt": "2025-01-15T11:15:00",
    "deleted": false
  },
  {
    "id": "TM-002",
    "teamId": "TEAM-001",
    "personnelId": "PER-003",
    "createdAt": "2025-01-15T11:16:00",
    "deleted": false
  },
  {
    "id": "TM-003",
    "teamId": "TEAM-002",
    "personnelId": "PER-003",
    "createdAt": "2025-01-15T11:17:00",
    "deleted": false
  },
  {
    "id": "TM-004",
    "teamId": "TEAM-003",
    "personnelId": "PER-004",
    "createdAt": "2025-01-15T11:18:00",
    "deleted": false
  },
  {
    "id": "TM-8FC85EBB",
    "teamId": "TEAM-001",
    "personnelId": "PER-004",
    "createdAt": "2026-01-18T05:06:56.793968",
    "deleted": false
  },
  {
    "id": "TM-A3B21EFE",
    "teamId": "TEAM-A04E29E7",
    "personnelId": "PER-001",
    "createdAt": "2026-01-18T05:36:11.722724",
    "deleted": false
  }
]